amit/__init__.py
amit/__main__.py
Topsis_Amit_102003053-1.0.0.dist-info/METADATA
Topsis_Amit_102003053-1.0.0.dist-info/WHEEL
Topsis_Amit_102003053-1.0.0.dist-info/entry_points.txt
Topsis_Amit_102003053-1.0.0.dist-info/top_level.txt
Topsis_Amit_102003053-1.0.0.dist-info/RECORD
